[
    {
        "task": "Know HTML, CSS, JavaScript,React and etc"
    },
    {
        "task": "coding languages"
    },
    {
        "task": "Create and test applications for websites"
    },
    {
        "task": "Collaborate"
    },
    {
        "task": "Present design specs"
    },
    {
        "task": "Work with graphics and other designers"
    },
    {
        "task": "Troubleshoot website problems."
    },
    {
        "task": "Maintain and update websites."
    },
    {
        "task": "Monitor website traffic."
    }
]